cdklabs/cdk_hyperledger_fabric_network/__init__.py
cdklabs/cdk_hyperledger_fabric_network/py.typed
cdklabs/cdk_hyperledger_fabric_network/_jsii/__init__.py
cdklabs/cdk_hyperledger_fabric_network/_jsii/cdk-hyperledger-fabric-network@0.8.990.jsii.tgz
cdklabs_cdk_hyperledger_fabric_network-0.8.990.dist-info/LICENSE
cdklabs_cdk_hyperledger_fabric_network-0.8.990.dist-info/METADATA
cdklabs_cdk_hyperledger_fabric_network-0.8.990.dist-info/WHEEL
cdklabs_cdk_hyperledger_fabric_network-0.8.990.dist-info/top_level.txt
cdklabs_cdk_hyperledger_fabric_network-0.8.990.dist-info/RECORD
