Metadata-Version: 2.1
Name: cdklabs.cdk-hyperledger-fabric-network
Version: 0.8.990
Summary: CDK construct to deploy a Hyperledger Fabric network running on Amazon Managed Blockchain
Home-page: https://github.com/cdklabs/cdk-hyperledger-fabric-network.git
Author: Amazon Web Services
License: MIT-0
Project-URL: Source, https://github.com/cdklabs/cdk-hyperledger-fabric-network.git
Classifier: Intended Audience :: Developers
Classifier: Operating System :: OS Independent
Classifier: Programming Language :: JavaScript
Classifier: Programming Language :: Python :: 3 :: Only
Classifier: Programming Language :: Python :: 3.9
Classifier: Programming Language :: Python :: 3.10
Classifier: Programming Language :: Python :: 3.11
Classifier: Typing :: Typed
Classifier: Development Status :: 5 - Production/Stable
Classifier: License :: OSI Approved
Requires-Python: ~=3.9
License-File: LICENSE
Requires-Dist: aws-cdk-lib <3.0.0,>=2.24.1
Requires-Dist: constructs <11.0.0,>=10.0.5
Requires-Dist: jsii <2.0.0,>=1.116.0
Requires-Dist: publication >=0.0.3
Requires-Dist: typeguard <4.3.0,>=2.13.3
